fib_ast/__init__.py
fib_ast/fib_ast.py
fib_ast-0.1.0.dist-info/LICENSE
fib_ast-0.1.0.dist-info/METADATA
fib_ast-0.1.0.dist-info/WHEEL
fib_ast-0.1.0.dist-info/RECORD
